{"type":"FeatureCollection", "features": [
{"type":"Feature","geometry":{"type":"Point","coordinates":[-94.74332745982011,34.94206149152157]},"properties":{"Condition":"Keep","NatuIntptv":"Yes","Hiking":"Yes","MountBike":"Yes","HP_Access":"Accessible","Surface":"Asphalt","InspctDate":"2011-10-22T00:00:00.000Z","Image_":"","Park_Name":"Lake Wister State Park","Feature":"TrailEndPoint","Name":"Handicap Trail/Heart Healthy Trail","Equestrain":"No","InspctDtt":"2011-10-22T00:00:00.000Z","TrailsType":"Hiking, Mountain Bike","GlobalID":"{0B9F2240-B0F8-411F-A698-6260956299AD}"}},
{"type":"Feature","geometry":{"type":"Point","coordinates":[-96.6290393991315,33.98246502695608]},"properties":{"Condition":"Keep","NatuIntptv":"No","Hiking":"Yes","MountBike":"No","HP_Access":"Useable","Surface":"Concrete","InspctDate":"2017-01-21T00:00:00.000Z","Image_":"","Park_Name":"Lake Texoma State Park","Feature":"TrailEndPoint","Name":"Heart Healthy Trail","Equestrain":"No","InspctDtt":"2017-01-21T00:00:00.000Z","TrailsType":"Hiking, Mountain Bike","GlobalID":"{964A002D-22C6-4E3A-AF76-6FC7D4818165}"}},
{"type":"Feature","geometry":{"type":"Point","coordinates":[-99.29862697828497,36.45648181109175]},"properties":{"Condition":"Keep","NatuIntptv":"No","Hiking":"Yes","MountBike":"Yes","HP_Access":"Non-Accessible","Surface":"Natural","InspctDate":"2012-06-06T00:00:00.000Z","Image_":"","Park_Name":"Boiling Springs State Park","Feature":"TrailEndPoint","Name":"Scout Trail/Heart Healthy Trail","Equestrain":"No","InspctDtt":"1899-11-30T00:00:00.000Z","TrailsType":"Hiking, Mountain Bike","GlobalID":"{12BA44A1-F0CC-4741-9BB3-3AA2B5BC7EBE}"}},
{"type":"Feature","geometry":{"type":"Point","coordinates":[-98.47251914308208,35.18073513993451]},"properties":{"Condition":"Keep","NatuIntptv":"No","Hiking":"Yes","MountBike":"Yes","HP_Access":"Non-Accessible","Surface":"Natural","InspctDate":"2015-06-01T00:00:00.000Z","Image_":"","Park_Name":"Fort Cobb State Park","Feature":"TrailEndPoint","Name":"Western Oaks Trails/Heart Healthy Trail","Equestrain":"No","InspctDtt":"2015-06-01T00:00:00.000Z","TrailsType":"Hiking, Mountain Bike","GlobalID":"{2F4DA4A6-7E00-470F-964D-70AFE3A46C3C}"}},
{"type":"Feature","geometry":{"type":"Point","coordinates":[-97.09565771423036,34.072098515800064]},"properties":{"Condition":"Keep","NatuIntptv":"","Hiking":"Yes","MountBike":"No","HP_Access":"Accessible","Surface":"Concrete","InspctDate":"1899-11-30T00:00:00.000Z","Image_":"","Park_Name":"Lake Murray State Park","Feature":"TrailEndPoint","Name":"Heart Healthy Trail","Equestrain":"No","InspctDtt":"1899-11-30T00:00:00.000Z","TrailsType":"Hiking","GlobalID":"{9C7BC4EE-8A76-4520-828F-5758D4CA4A33}"}},
{"type":"Feature","geometry":{"type":"Point","coordinates":[-99.14820437656844,36.69850617324062]},"properties":{"Condition":"Keep","NatuIntptv":"No","Hiking":"Yes","MountBike":"No","HP_Access":"Non-Accessible","Surface":"Natural","InspctDate":"2012-05-30T00:00:00.000Z","Image_":"","Park_Name":"Alabaster Caverns State Park","Feature":"TrailEndPoint","Name":"Raptorsroost Trail/Heart Healthy Trail","Equestrain":"No","InspctDtt":"2012-05-30T00:00:00.000Z","TrailsType":"Hiking","GlobalID":"{AA1B33FE-3F42-4483-BD1D-4B656CA31D2F}"}},
{"type":"Feature","geometry":{"type":"Point","coordinates":[-98.44211423024784,35.932437312422195]},"properties":{"Condition":"Keep","NatuIntptv":"No","Hiking":"Yes","MountBike":"No","HP_Access":"Non-Accessible","Surface":"Natural","InspctDate":"2009-12-11T00:00:00.000Z","Image_":"","Park_Name":"Roman Nose State Park","Feature":"TrailEndPoint","Name":"Three Springs Trail/Heart Healthy Trail","Equestrain":"No","InspctDtt":"2009-12-11T00:00:00.000Z","TrailsType":"Hiking","GlobalID":"{4F87D43E-FB63-43CD-9EE3-C2FC893D2E9A}"}},
{"type":"Feature","geometry":{"type":"Point","coordinates":[-97.24718268437248,35.239043843020006]},"properties":{"Condition":"Keep","NatuIntptv":"Yes","Hiking":"Yes","MountBike":"No","HP_Access":"Non-Accessible","Surface":"Natural","InspctDate":"1899-11-30T00:00:00.000Z","Image_":"","Park_Name":"Lake Thunderbird State Park","Feature":"TrailEndPoint","Name":"Hog Creek Trail/Heart Healthy Trail","Equestrain":"No","InspctDtt":"1899-11-30T00:00:00.000Z","TrailsType":"Interpretive, Hiking","GlobalID":"{E6BD88E7-39C9-468F-99D4-31AA63624501}"}},
{"type":"Feature","geometry":{"type":"Point","coordinates":[-99.20089077042057,35.532246782779424]},"properties":{"Condition":"Keep","NatuIntptv":"","Hiking":"Yes","MountBike":"Yes","HP_Access":"Non-Accessible","Surface":"Natural","InspctDate":"1899-11-30T00:00:00.000Z","Image_":"","Park_Name":"Foss State Park","Feature":"TrailEndPoint","Name":"Heart Healthy Trail","Equestrain":"No","InspctDtt":"1899-11-30T00:00:00.000Z","TrailsType":"Hiking","GlobalID":"{AED54290-8318-4B33-A47E-916E3EDA22D8}"}},
{"type":"Feature","geometry":{"type":"Point","coordinates":[-98.14035189090036,36.73830251810912]},"properties":{"Condition":"","NatuIntptv":"","Hiking":"Yes","MountBike":"Yes","HP_Access":"Non-Accessible","Surface":"Natural","InspctDate":"2020-03-05T00:00:00.000Z","Image_":"","Park_Name":"Great Salt Plains State Park","Feature":"TrailEndPoint","Name":"Heart Healthy Trail","Equestrain":"Yes","InspctDtt":"1899-11-30T00:00:00.000Z","TrailsType":"Hiking, Mountain Bike, Equestrian","GlobalID":"{CA7EEE3D-2424-462D-9E22-EB9BDA959AC2}"}},
{"type":"Feature","geometry":{"type":"Point","coordinates":[-98.97803993491719,34.748838253381884]},"properties":{"Condition":"Keep","NatuIntptv":"","Hiking":"Yes","MountBike":"No","HP_Access":"","Surface":"Concrete","InspctDate":"1899-11-30T00:00:00.000Z","Image_":"","Park_Name":"Great Plains State Park","Feature":"TrailEndPoint","Name":"Heart Healthy Trail","Equestrain":"No","InspctDtt":"1899-11-30T00:00:00.000Z","TrailsType":"Hiking","GlobalID":"{BE2FCF1B-2F9D-456B-AFC4-EF5328858093}"}},
{"type":"Feature","geometry":{"type":"Point","coordinates":[-94.89195816825061,36.62702021918588]},"properties":{"Condition":"Keep","NatuIntptv":"Yes","Hiking":"Yes","MountBike":"No","HP_Access":"Accessible","Surface":"Asphalt","InspctDate":"2011-08-15T00:00:00.000Z","Image_":"","Park_Name":"Grand Lake State Park (Bernice Area)","Feature":"TrailEndPoint","Name":"Nature Trail/Heart Healthy Trail","Equestrain":"No","InspctDtt":"1899-12-30T00:00:00.000Z","TrailsType":"Interpretive, Hiking","GlobalID":"{BE9A7039-9A27-41BA-9B02-0C8291D28E41}"}}
]}